Workbook

Sheet 📊 Dashboard
A1: 🚀 NEXOR ADVISORY — Plan Formation NoCode + IA · Romaric O.
A2: Alegria : 6h-8h (2h/j) · Théo : 20h-23h (3h/j) · Weekends : 8h-12h & 19h-23h · Démarrage : 12 mai 2026
A3: Sessions Alegria | E3: Sessions Théo | I3: Jours Restants | M3: Contrats NEXOR
A4: =COUNTIF('👧 Alegria'!H:H,"✓") | E4: =COUNTIF('👦 Théo'!H:H,"✓") | I4: =MAX(0,30-INT((TODAY()-DATE(2026,5,12)))) | M4: =COUNTIF('🚀 NEXOR Pipeline'!E:E,"Signé")
A8: 📅 PLANNING HEBDOMADAIRE FIXE
B9: Lundi | C9: Mardi | D9: Mercredi | E9: Jeudi | F9: Vendredi | G9: Samedi | H9: Dimanche
A10: 6h00 – 6h30 | B10: 🏃 Sport | C10: 🏃 Sport | D10: 🏃 Sport | E10: 🏃 Sport | F10: 🏃 Sport | G10: ─ | H10: ─
A11: 6h30 – 8h00 | B11: 👧 ALEGRIA NoCode/IA | C11: 👧 ALEGRIA NoCode/IA | D11: 👧 ALEGRIA NoCode/IA | E11: 👧 ALEGRIA NoCode/IA | F11: 👧 ALEGRIA NoCode/IA | G11: ─ | H11: ─
A12: 8h00 – 19h00 | B12: Consulting NEXOR/ORNET | C12: Consulting NEXOR/ORNET | D12: Consulting NEXOR/ORNET | E12: Consulting NEXOR/ORNET | F12: Consulting NEXOR/ORNET | G12: 8h-12h 🚀 NEXOR Prospection+Build | H12: 8h-12h 🔧 Deep Work NoCode perso
A13: 19h00 – 20h00 | B13: Repas + transition | C13: Repas + transition | D13: Repas + transition | E13: Repas + transition | F13: Repas + transition | G13: 12h-19h Famille / Repos | H13: 12h-19h Famille / Repos
A14: 20h00 – 23h00 | B14: 👦 THÉO NoCode/IA | C14: 👦 THÉO NoCode/IA | D14: 👦 THÉO NoCode/IA | E14: 👦 THÉO NoCode/IA | F14: 👦 THÉO NoCode/IA | G14: 19h-23h 🚀 NEXOR Build+Contenu | H14: 19h-23h 🔧 WifiAudit + Bilan
A16: 📈 PROGRESSION GLOBALE
A17: Personne | B17: Sessions planifiées | C17: Réalisées | D17: Taux % | E17: Semaine en cours | F17: Prochain objectif
A18: 👧 Alegria | B18: 20 | C18: =COUNTIF('👧 Alegria'!H:H,"✓") | D18: =IFERROR(ROUND(C18/B18*100,0)&"%","0%")
A19: 👦 Théo | B19: 20 | C19: =COUNTIF('👦 Théo'!H:H,"✓") | D19: =IFERROR(ROUND(C19/B19*100,0)&"%","0%")
A20: 🚀 Romaric Weekend | B20: 8 | C20: =COUNTIF('📅 Weekends'!E:E,"✓") | D20: =IFERROR(ROUND(C20/B20*100,0)&"%","0%")

Sheet 👧 Alegria
A1: 👧 ALEGRIA — Formation NoCode + IA · 6h00 – 8h00 (2h/session)
A2: Niveau : Débutante · Durée : 4 semaines · Outils : n8n → Claude API → Make → Bubble.io
A3: S# | B3: Date | C3: Jour | D3: Thème / Outil | E3: Objectif de la session | F3: Contenu détaillé (étapes) | G3: Livrable attendu | H3: ✅ | I3: Score | J3: Durée | K3: Bloc | L3: Notes
A4: ━━━ SEMAINE 1 — n8n Fondations (Débutante → Autonome sur l'automatisation basique) ━━━
A5: 1 | B5: 12/05 | C5: Lun | D5: n8n — Interface & 1er workflow | E5: Comprendre l'interface n8n, créer un 1er workflow fonctionnel | F5: 1. Ouvrir n8n (10.30.20.2) 2. Découvrir : Canvas, nodes, connexions 3. Créer un trigger Manuel 4. Ajouter un node Email ou Telegram 5. Exécuter et voir le résultat | G5: Workflow 'Bonjour monde' qui envoie un message | H5: ✗ | I5: ─ | J5: 2h | K5: 6h-8h
A6: 1 | B6: 13/05 | C6: Mar | D6: n8n — Scheduler & automatisation | E6: Déclencher automatiquement un workflow à heure fixe | F6: 1. Node Scheduler : configurer 6h45 chaque matin 2. Node Set : définir un message variable 3. Node IF : condition simple (jour de semaine ?) 4. Envoyer un message différent selon le jour 5. Tester en changeant l'heure | G6: Workflow 'Bon matin' automatique chaque jour à 6h45 | H6: ✗ | I6: ─ | J6: 2h | K6: 6h-8h
A7: 1 | B7: 14/05 | C7: Mer | D7: n8n — HTTP Request & APIs | E7: Appeler une API externe et utiliser les données | F7: 1. C'est quoi une API ? (explication simple) 2. Node HTTP Request : méthode GET 3. Appeler API météo (wttr.in) : récupérer la météo Paris 4. Extraire les données JSON 5. Formater et envoyer le résultat | G7: Workflow 'Météo du jour' envoyé chaque matin | H7: ✗ | I7: ─ | J7: 2h | K7: 6h-8h
A8: 1 | B8: 15/05 | C8: Jeu | D8: n8n — Webhook & formulaire | E8: Recevoir des données depuis un formulaire et les traiter | F8: 1. Node Webhook : créer un endpoint URL 2. Tester avec un formulaire simple (Google Form ou Tally) 3. Extraire les champs du formulaire 4. Sauvegarder dans Google Sheets ou Notion 5. Envoyer une confirmation automatique | G8: Formulaire → n8n → sauvegarde + email de confirmation | H8: ✗ | I8: ─ | J8: 2h | K8: 6h-8h
A9: 1 | B9: 16/05 | C9: Ven | D9: PROJET S1 — Workflow complet | E9: Assembler tout ce qu'on a appris en un workflow réel | F9: 1. Choisir un cas d'usage simple (son idée) 2. Dessiner le workflow sur papier d'abord 3. Implémenter dans n8n (30 min) 4. Tester et corriger (20 min) 5. Présenter à voix haute (10 min) | G9: Mini-projet S1 fonctionnel + explication orale | H9: ✗ | I9: ─ | J9: 2h | K9: 6h-8h
A10: ━━━ SEMAINE 2 — Claude API + IA (Créer des agents IA pratiques) ━━━
A11: 2 | B11: 19/05 | C11: Lun | D11: Claude API — Introduction | E11: Comprendre ce qu'est une IA et faire son premier appel | F11: 1. C'est quoi une IA générative ? (10 min) 2. Créer un compte Anthropic (si pas encore fait) 3. Dans n8n : node HTTP Request vers api.anthropic.com 4. Envoyer un message simple et voir la réponse 5. Modifier le prompt et observer les différences | G11: Premier appel Claude API dans n8n → réponse affichée | H11: ✗ | I11: ─ | J11: 2h | K11: 6h-8h
A12: 2 | B12: 20/05 | C12: Mar | D12: Claude API — Générer du texte | E12: Générer des emails, résumés et textes automatiquement | F12: 1. System prompt : définir le rôle de l'IA 2. User prompt : la demande précise 3. Générer un email professionnel automatiquement 4. Générer un résumé d'un texte long 5. Faire varier le ton (formel, amical, court) | G12: Workflow : texte en entrée → résumé en sortie | H12: ✗ | I12: ─ | J12: 2h | K12: 6h-8h
A13: 2 | B13: 21/05 | C13: Mer | D13: Claude API — Analyser des données | E13: Envoyer un fichier et obtenir une analyse intelligente | F13: 1. Transformer un CSV simple en texte pour Claude 2. Demander : 'Quels sont les 3 points importants ?' 3. Structurer la réponse (liste, tableau) 4. Appliquer sur une vraie donnée (facture, rapport) 5. Sauvegarder l'analyse dans Notion | G13: Workflow : fichier → analyse IA → sauvegarde Notion | H13: ✗ | I13: ─ | J13: 2h | K13: 6h-8h
A14: 2 | B14: 22/05 | C14: Jeu | D14: Claude API — Créer du contenu | E14: Générer des posts, newsletters et contenus marketing | F14: 1. Prompt pour générer un post LinkedIn 2. Ajouter des émojis et une structure claire 3. Faire varier le sujet automatiquement 4. Workflow : thème du jour → post LinkedIn prêt 5. Programmer l'envoi à une heure fixe | G14: Workflow : thème → post LinkedIn généré automatiquement | H14: ✗ | I14: ─ | J14: 2h | K14: 6h-8h
A15: 2 | B15: 23/05 | C15: Ven | D15: PROJET S2 — Agent IA simple | E15: Créer son premier agent IA qui répond à des questions | F15: 1. Définir le cas d'usage (son choix) 2. Rédiger le system prompt parfait 3. Créer le workflow complet 4. Tester avec 5 questions différentes 5. Présenter le résultat | G15: Agent IA fonctionnel sur un sujet choisi | H15: ✗ | I15: ─ | J15: 2h | K15: 6h-8h
A16: ━━━ SEMAINE 3 — Make + Intégrations (Pipeline multi-outils) ━━━
A17: 3 | B17: 26/05 | C17: Lun | D17: Make — Interface & 1er scénario | E17: Découvrir Make et créer son premier scénario | F17: 1. Créer un compte Make (make.com) 2. Interface : modules, connexions, filtres 3. Différence Make vs n8n (quand utiliser quoi) 4. Premier scénario : form → email 5. Activer et tester | G17: Scénario Make : formulaire → email de confirmation | H17: ✗ | I17: ─ | J17: 2h | K17: 6h-8h
A18: 3 | B18: 27/05 | C18: Mar | D18: Make — Connexions apps | E18: Connecter Google, Notion, Gmail dans Make | F18: 1. Connecter Google Sheets (authentification) 2. Connecter Gmail 3. Scénario : nouveau contact → fiche Notion + email 4. Ajouter un filtre conditionnel 5. Programmer l'exécution automatique | G18: Scénario : nouveau contact → Notion + Gmail | H18: ✗ | I18: ─ | J18: 2h | K18: 6h-8h
A19: 3 | B19: 28/05 | C19: Mer | D19: Make — Pipeline automatisé | E19: Créer un pipeline de traitement complet | F19: 1. Déclencher depuis un webhook 2. Transformer les données (formatage) 3. Router selon conditions (clients VIP vs standards) 4. Sauvegarder dans deux endroits différents 5. Envoyer une notification différente selon le type | G19: Pipeline complet avec routing et notifications | H19: ✗ | I19: ─ | J19: 2h | K19: 6h-8h
A20: 3 | B20: 29/05 | C20: Jeu | D20: Make + n8n + Claude — Combiner les outils | E20: Créer un workflow hybride multi-outils | F20: 1. n8n reçoit un webhook 2. Appelle Claude API pour analyser 3. Envoie le résultat à Make 4. Make sauvegarde et notifie 5. Tester le pipeline complet | G20: Workflow hybride n8n → Claude → Make fonctionnel | H20: ✗ | I20: ─ | J20: 2h | K20: 6h-8h
A21: 3 | B21: 30/05 | C21: Ven | D21: PROJET S3 — Pipeline commercial | E21: Automatiser un vrai processus business | F21: 1. Choisir : lead entrant, commande, support... 2. Mapper le processus actuel 3. Construire l'automatisation complète 4. Tester avec des données réelles 5. Calculer le temps économisé/semaine | G21: Pipeline commercial automatisé + calcul ROI | H21: ✗ | I21: ─ | J21: 2h | K21: 6h-8h
A22: ━━━ SEMAINE 4 — Bubble.io + Projet Final (Construire une vraie app) ━━━
A23: 4 | B23: 02/06 | C23: Lun | D23: Bubble.io — Interface & design | E23: Créer sa première page web sans coder | F23: 1. Créer un compte Bubble.io 2. Interface : éditeur, responsive, éléments 3. Ajouter : texte, boutons, images 4. Créer une page d'accueil simple 5. Prévisualiser en mode mobile | G23: Page d'accueil simple et responsive dans Bubble | H23: ✗ | I23: ─ | J23: 2h | K23: 6h-8h
A24: 4 | B24: 03/06 | C24: Mar | D24: Bubble.io — Base de données | E24: Stocker et afficher des données dynamiques | F24: 1. Data types dans Bubble (tables, champs) 2. Créer une table 'Contacts' 3. Formulaire pour ajouter des contacts 4. Afficher la liste des contacts 5. Ajouter recherche et filtres | G24: Mini-app de gestion de contacts dans Bubble | H24: ✗ | I24: ─ | J24: 2h | K24: 6h-8h
A25: 4 | B25: 04/06 | C25: Mer | D25: Bubble.io — Workflows & logique | E25: Ajouter de l'interactivité et des actions | F25: 1. Workflows Bubble : quand/quoi faire 2. Bouton → action (créer, modifier, supprimer) 3. Conditions : afficher si connecté 4. Envoyer un email depuis Bubble 5. Appeler n8n depuis Bubble | G25: App interactive avec actions et conditions | H25: ✗ | I25: ─ | J25: 2h | K25: 6h-8h
A26: 4 | B26: 05/06 | C26: Jeu | D26: Bubble.io — API Connector | E26: Connecter Bubble à des services externes | F26: 1. Plugin API Connector dans Bubble 2. Appeler Claude API depuis Bubble 3. Afficher la réponse IA dans l'interface 4. Appeler n8n webhook depuis un bouton 5. Tester le flux complet | G26: App Bubble qui appelle Claude API et affiche le résultat | H26: ✗ | I26: ─ | J26: 2h | K26: 6h-8h
A27: 4 | B27: 06/06 | C27: Ven | D27: PROJET FINAL — Application complète | E27: Créer une vraie app NoCode de A à Z | F27: 1. Choisir le projet (son idée ou cas NEXOR) 2. Concevoir : pages, données, workflows 3. Construire (60 min) 4. Connecter les automatisations (20 min) 5. PRÉSENTATION FINALE (20 min) | G27: Application complète + présentation 20 min | H27: ✗ | I27: ─ | J27: 2h | K27: 6h-8h

Sheet 👦 Théo
A1: 👦 THÉO — Formation NoCode + IA Avancé · 20h00 – 23h00 (3h/session)
A2: Niveau : Intermédiaire · Durée : 4 semaines · Outils : n8n Avancé → Agents IA → Make Expert → Bubble Pro
A3: S# | B3: Date | C3: Jour | D3: Thème / Outil | E3: Objectif (niveau expert) | F3: Contenu détaillé (3h) | G3: Livrable facturable | H3: ✅ | I3: Score | J3: Durée | K3: Bloc | L3: Notes
A4: ━━━ SEMAINE 1 — n8n Avancé (Niveau professionnel, workflows facturables) ━━━
A5: 1 | B5: 12/05 | C5: Lun | D5: n8n Avancé — Expressions & JSON | E5: Maîtriser les expressions n8n et la manipulation de données JSON complexes | F5: 1. Expressions {{ }} : tout savoir (40 min) 2. Fonctions JS inline : .split(), .map(), .filter() 3. Manipulation JSON : nested objects, arrays 4. Node Function/Code : JavaScript dans n8n 5. Exercice : transformer données CatC brutes en rapport structuré 6. Débogage : Error Trigger + logs | G5: Transformer un export CatC JSON complexe en rapport lisible | H5: ✗ | I5: ─ | J5: 3h | K5: 20h-23h
A6: 1 | B6: 13/05 | C6: Mar | D6: n8n — APIs Avancées & Auth | E6: Maîtriser tous les types d'authentification et gérer les APIs complexes | F6: 1. Auth types : Bearer Token, OAuth2, API Key, Basic 2. Pagination automatique : loop pour 1000+ résultats 3. Rate limiting : délais entre appels 4. Gestion d'erreurs : retry, fallback, alertes 5. Node HTTP Request avancé : headers, query params 6. Exercice : inventaire complet CatC paginé | G6: Script d'inventaire CatC complet avec auth + pagination | H6: ✗ | I6: ─ | J6: 3h | K6: 20h-23h
A7: 1 | B7: 14/05 | C7: Mer | D7: n8n — Sub-workflows & Architecture | E7: Architecturer des solutions complexes et modulaires | F7: 1. Sub-workflows : créer des modules réutilisables 2. Exécutions en parallèle : Split In Batches 3. Wait node : workflows asynchrones 4. Variables globales : partager des données 5. Webhook sécurisé : validation signatures 6. Exercice : refactoriser un workflow existant en modules | G7: Architecture modulaire réutilisable pour 3 cas d'usage NEXOR | H7: ✗ | I7: ─ | J7: 3h | K7: 20h-23h
A8: 1 | B8: 15/05 | C8: Jeu | D8: n8n — Workflow Professionnel | E8: Construire un workflow complet de niveau production | F8: 1. Cas d'usage réel : rapport réseau automatisé 2. Ingestion données CatC/WLC via API 3. Transformation et scoring (votre formule RF) 4. Génération PDF ou email formaté 5. Gestion erreurs + alertes Slack 6. Tests unitaires manuels + documentation | G8: Workflow 'Rapport réseau automatique' prêt à livrer | H8: ✗ | I8: ─ | J8: 3h | K8: 20h-23h
A9: 1 | B9: 16/05 | C9: Ven | D9: LIVRABLE S1 — Workflow Facturable | E9: Finaliser et packager un workflow vendable | F9: 1. Révision et polish du workflow S1 (45 min) 2. Créer la documentation utilisateur (30 min) 3. Packager : guide d'installation + credentials 4. Estimer le prix (combien vaut ce workflow ?) 5. Préparer une démo de 5 minutes 6. Répéter la démo à voix haute | G9: Workflow documenté + démo 5 min + prix estimé | H9: ✗ | I9: ─ | J9: 3h | K9: 20h-23h
A10: ━━━ SEMAINE 2 — Agents IA Avancés (Construire des agents qui se vendent) ━━━
A11: 2 | B11: 19/05 | C11: Lun | D11: Agents IA — Architecture & Mémoire | E11: Concevoir des agents IA robustes avec mémoire et contexte | F11: 1. Architecture agent : system prompt, mémoire, outils 2. Mémoire contextuelle : maintenir l'historique 3. Chain of thought : raisonner étape par étape 4. Structured output : forcer un format JSON 5. Gestion de tokens : optimiser les coûts 6. Exercice : agent qui analyse des logs réseau | G11: Agent analyseur de logs avec mémoire de contexte | H11: ✗ | I11: ─ | J11: 3h | K11: 20h-23h
A12: 2 | B12: 20/05 | C12: Mar | D12: Agent — Qualification Leads IA | E12: Construire l'agent de qualification commerciale NEXOR | F12: 1. Objectif : email entrant → qualification automatique 2. Extraire : société, besoin, budget, urgence 3. Scorer le lead (1-10) selon critères NEXOR 4. Enrichir : rechercher l'entreprise (API Clearbit) 5. Créer la fiche dans Notion CRM 6. Envoyer une réponse personnalisée automatique | G12: Agent de qualification leads NEXOR opérationnel | H12: ✗ | I12: ─ | J12: 3h | K12: 20h-23h
A13: 2 | B13: 21/05 | C13: Mer | D13: Agent — Support IT Réseau | E13: Construire l'agent de diagnostic réseau intelligent | F13: 1. Objectif : alerte réseau → diagnostic → action 2. Parser les alertes SolarWinds/CatC 3. Base de connaissances (FAQ réseau en prompt) 4. Diagnostic automatique selon type d'alerte 5. Créer un ticket Notion/Jira automatiquement 6. Escalade si critique (Slack + SMS) | G13: Agent support IT réseau avec escalade automatique | H13: ✗ | I13: ─ | J13: 3h | K13: 20h-23h
A14: 2 | B14: 22/05 | C14: Jeu | D14: RAG — Base de connaissances | E14: Créer un agent qui cherche dans une base documentaire | F14: 1. C'est quoi le RAG ? (30 min) 2. Charger des documents dans le contexte Claude 3. Technique : embed + search simplifié en n8n 4. Cas d'usage : agent répond sur doc technique 5. Appliquer sur documentation Cisco/CatC 6. Tester avec 10 questions réelles | G14: Agent RAG sur documentation réseau Cisco | H14: ✗ | I14: ─ | J14: 3h | K14: 20h-23h
A15: 2 | B15: 23/05 | C15: Ven | D15: LIVRABLE S2 — Agent IA Facturable | E15: Agent IA complet prêt pour un client NEXOR | F15: 1. Choisir l'agent le plus avancé de la semaine 2. Raffiner le system prompt (perfectionniste) 3. Ajouter gestion erreurs + fallback 4. Documenter : cas d'usage, limitations, prix 5. Démo 10 minutes simulant une vraie présentation client 6. Répéter jusqu'à fluidité totale | G15: Agent IA documenté + démo client 10 min | H15: ✗ | I15: ─ | J15: 3h | K15: 20h-23h
A16: ━━━ SEMAINE 3 — Make Expert + Projet Client Réel (Livraison + facturation) ━━━
A17: 3 | B17: 26/05 | C17: Lun | D17: Make Expert — Routeurs & Iterators | E17: Maîtriser les fonctionnalités avancées de Make | F17: 1. Router : aiguiller selon conditions multiples 2. Iterator : traiter élément par élément 3. Aggregator : regrouper des résultats 4. Array Aggregator : construire des tableaux 5. Error handling avancé : ignore/resume/break 6. Exercice : traiter une liste de 50 leads | G17: Scénario Make traitant 50 leads avec routage et agrégation | H17: ✗ | I17: ─ | J17: 3h | K17: 20h-23h
A18: 3 | B18: 27/05 | C18: Mar | D18: Make — Architecture Multi-outils | E18: Décider de la meilleure architecture selon le cas | F18: 1. Matrice de décision : n8n vs Make vs les deux 2. Cas où Make est meilleur que n8n (et vice versa) 3. Intégrations natives Make : Stripe, HubSpot, Slack 4. Construire un CRM léger : Make + Airtable + Gmail 5. Webhook bidirectionnel n8n ↔ Make 6. Performance et coûts : calculer le prix mensuel | G18: CRM automatisé Make + Airtable + Gmail fonctionnel | H18: ✗ | I18: ─ | J18: 3h | K18: 20h-23h
A19: 3 | B19: 28/05 | C19: Mer | D19: PROJET CLIENT NEXOR — Jour 1 | E19: Démarrer l'exécution d'un vrai projet NEXOR | F19: 1. Brief projet (définir avec Romaric) 2. Architecture technique : schéma de solution 3. Choix des outils (n8n / Make / Bubble / Claude) 4. Estimation temps et livrables 5. Commencer l'implémentation 6. Point d'avancement avec Romaric | G19: Architecture validée + 30% du projet implémenté | H19: ✗ | I19: ─ | J19: 3h | K19: 20h-23h
A20: 3 | B20: 29/05 | C20: Jeu | D20: PROJET CLIENT NEXOR — Jour 2 | E20: Avancer et raffiner l'implémentation | F20: 1. Suite de l'implémentation (80% objectif) 2. Tests avec données réelles du client 3. Gestion des cas d'erreur 4. Documentation technique (pour le client) 5. Préparation de la présentation 6. Point final avec Romaric | G20: Projet à 80% + documentation technique | H20: ✗ | I20: ─ | J20: 3h | K20: 20h-23h
A21: 3 | B21: 30/05 | C21: Ven | D21: LIVRABLE S3 — Projet Livré | E21: Finaliser et livrer le projet client | F21: 1. Finaliser les 20% restants (45 min) 2. Tests finaux complets 3. Documentation utilisateur (guide pratique) 4. Présentation client (simulation) 5. Facturation : créer la facture NEXOR 6. Retour d'expérience : qu'est-ce qu'on ferait différemment ? | G21: Projet client livré + facture NEXOR émise | H21: ✗ | I21: ─ | J21: 3h | K21: 20h-23h
A22: ━━━ SEMAINE 4 — Bubble.io Pro + Industrialisation (Autonomie totale) ━━━
A23: 4 | B23: 02/06 | C23: Lun | D23: Bubble.io Avancé — API & Données | E23: Construire des apps connectées à des APIs externes | F23: 1. API Connector : configurer des calls complexes 2. Appeler Claude API depuis Bubble 3. Appeler n8n webhook depuis Bubble 4. Base de données Bubble : relations, privacy rules 5. Repeating Group : listes dynamiques 6. Exercice : dashboard avec données live | G23: Dashboard Bubble avec données live via API | H23: ✗ | I23: ─ | J23: 3h | K23: 20h-23h
A24: 4 | B24: 03/06 | C24: Mar | D24: WifiAudit AI — Interface Front-End | E24: Construire l'interface client de WifiAudit AI | F24: 1. Pages : upload, résultats, historique, profil 2. Upload de fichier : connecter au backend FastAPI 3. Afficher les scores RF : progress bars, couleurs 4. Graphiques : plugin Chart.js dans Bubble 5. Export PDF depuis l'interface 6. Responsive mobile | G24: Interface WifiAudit AI fonctionnelle dans Bubble | H24: ✗ | I24: ─ | J24: 3h | K24: 20h-23h
A25: 4 | B25: 04/06 | C25: Mer | D25: Bubble.io — Stripe & Abonnements | E25: Intégrer les paiements dans une app Bubble | F25: 1. Plugin Stripe dans Bubble 2. Créer les 3 plans (Starter/Pro/Enterprise) 3. Gestion des abonnements : start, cancel, upgrade 4. Webhook Stripe → mise à jour statut client 5. Espace membre sécurisé selon abonnement 6. Test complet du checkout | G25: Checkout Stripe fonctionnel dans WifiAudit interface | H25: ✗ | I25: ─ | J25: 3h | K25: 20h-23h
A26: 4 | B26: 05/06 | C26: Jeu | D26: Industrialisation — Documenter & Scaler | E26: Transformer une compétence en produit vendable | F26: 1. Template de projet : checklist démarrage client 2. Estimation systématique : grille de tarification 3. Contrat type pour projets NoCode 4. Onboarding client : guide 'comment utiliser' 5. Maintenance et support : procédures 6. Portfolio : documenter les 3 meilleurs projets | G26: Grille de tarification + 3 fiches projet portfolio | H26: ✗ | I26: ─ | J26: 3h | K26: 20h-23h
A27: 4 | B27: 06/06 | C27: Ven | D27: LIVRABLE FINAL — Autonomie Totale | E27: Valider l'autonomie complète sur tous les outils | F27: 1. Exercice surprise : construire un workflow inconnu 2. Sans aide, en 90 minutes 3. Présentation du travail de 4 semaines 4. Démo combinée : n8n + Claude + Make + Bubble 5. Bilan : forces, lacunes, prochaines étapes 6. Définir le plan de progression mois 2 | G27: Démo finale 20 min + rapport d'évaluation complet | H27: ✗ | I27: ─ | J27: 3h | K27: 20h-23h

Sheet 📅 Weekends
A1: 🚀 ROMARIC — Weekends NEXOR + NoCode Perso · 8h-12h & 19h-23h
A2: Date | B2: Jour | C2: Bloc | D2: Activité principale | E2: ✅ | F2: CA généré (€) | G2: Prospects contactés | H2: Livrables | I2: Notes
A3: 16/05 | B3: Sam | C3: 8h-12h | D3: Bilan S1 + Prépa cours S2 (Alegria/Théo) + 20 prospects LinkedIn contactés | E3: ✗
A4: 16/05 | B4: Sam | C4: 19h-23h | D4: NoCode perso : reproduire les workflows de la semaine + Morning Content Workflow v1 | E4: ✗
A5: 17/05 | B5: Dim | C5: 8h-12h | D5: Deep work NoCode : LangChain intro + WifiAudit AI : parse_catc_export.py | E5: ✗
A6: 17/05 | B6: Dim | C6: 19h-23h | D6: Bilan semaine 1 + plan S2 + trésorerie + relances prospects | E6: ✗
A7: 23/05 | B7: Sam | C7: 8h-12h | D7: NEXOR : affiner l'offre + 30 nouveaux contacts LinkedIn + 5 emails qualifiés | E7: ✗
A8: 23/05 | B8: Sam | C8: 19h-23h | D8: Construire la démo NEXOR Network Intelligence (n8n + CatC + rapport PDF) | E8: ✗
A9: 24/05 | B9: Dim | C9: 8h-12h | D9: Deep work : Agents IA + WifiAudit scoring RF + entretien prospect si dispo | E9: ✗
A10: 24/05 | B10: Dim | C10: 19h-23h | D10: Proposition commerciale NEXOR + suivi contrat en cours + plan S3 | E10: ✗
A11: 30/05 | B11: Sam | C11: 8h-12h | D11: NEXOR : relances + nouveaux contacts + prép démo semaine + contenu LinkedIn 2 posts | E11: ✗
A12: 30/05 | B12: Sam | C12: 19h-23h | D12: Construire Make + connecter pipeline commercial NEXOR complet | E12: ✗
A13: 31/05 | B13: Dim | C13: 8h-12h | D13: Bubble.io : démarrer interface WifiAudit AI + Deep work perso | E13: ✗
A14: 31/05 | B14: Dim | C14: 19h-23h | D14: Bilan mai complet + plan juin + trésorerie ORNET + contact avocat | E14: ✗
... A18: 07/06 | B18: Dim | C18: 19h-23h | D18: Bilan formation 4 semaines + évaluation Alegria/Théo + plan mois 2 | E18: ✗
A20: TOTAL CA GÉNÉRÉ SUR LES WEEKENDS | F20: =SUM(F3:F18)

Sheet 🚀 NEXOR Pipeline
A1: 🚀 NEXOR ADVISORY — Pipeline Commercial & Trésorerie
A2: PROSPECTS & OPPORTUNITÉS
A3: Prospect | B3: Société | C3: Poste | D3: Offre ciblée | E3: Statut | F3: Montant € | G3: Date contact | H3: Prochaine action | I3: Probabilité % | J3: CA pondéré € | K3: Notes
J4: =IFERROR(F4*H4/100,0)
J5: =IFERROR(F5*H5/100,0)
J6: =IFERROR(F6*H6/100,0)
J7: =IFERROR(F7*H7/100,0)
J8: =IFERROR(F8*H8/100,0)
J9: =IFERROR(F9*H9/100,0)
J10: =IFERROR(F10*H10/100,0)
J11: =IFERROR(F11*H11/100,0)
J12: =IFERROR(F12*H12/100,0)
J13: =IFERROR(F13*H13/100,0)
J14: =IFERROR(F14*H14/100,0)
J15: =IFERROR(F15*H15/100,0)
A16: TOTAL PIPELINE | F16: =SUM(F4:F15) | J16: =SUM(J4:J15)
A19: SUIVI TRÉSORERIE — REMBOURSEMENT DETTE ORNET
A20: Mois | B20: CA NEXOR | C20: Sous-trait→ORNET | D20: Apurement URSSAF | E20: Apurement TVA | F20: Charges NEXOR | G20: Net disponible | H20: Dette restante | I20: Commentaire
A21: Mai 26 | G21: =B21-C21-D21-E21-F21 | H21: 100000
A22: Juin 26 | G22: =B22-C22-D22-E22-F22 | H22: =H21-D22-E22
A23: Juil 26 | G23: =B23-C23-D23-E23-F23 | H23: =H22-D23-E23
A24: Août 26 | G24: =B24-C24-D24-E24-F24 | H24: =H23-D24-E24
A25: Sept 26 | G25: =B25-C25-D25-E25-F25 | H25: =H24-D25-E25
A26: Oct 26 | G26: =B26-C26-D26-E26-F26 | H26: =H25-D26-E26
A27: Nov 26 | G27: =B27-C27-D27-E27-F27 | H27: =H26-D27-E27
A28: Déc 26 | G28: =B28-C28-D28-E28-F28 | H28: =H27-D28-E28

Sheet 🤖 Automations n8n
A1: 🤖 AUTOMATIONS n8n — Plan d'implémentation & Suivi
A2: # | B2: Nom du workflow | C2: Trigger | D2: Description | E2: Outil(s) | F2: Priorité | G2: ✅ Créé | H2: Testé | I2: En prod | J2: Valeur estimée €
A3: 1 | B3: 🌅 Morning Brief Alegria | C3: Planifié 5h50/sem | D3: Génère et envoie le brief de la session Alegria du jour (thème, étapes, objectif) | E3: n8n + Claude API | F3: 🔴 URGENT | G3: ✗ | H3: ✗ | I3: ✗ | J3: ─
A4: 2 | B4: 🌙 Evening Brief Théo | C4: Planifié 19h50/sem | D4: Génère et envoie le brief de la session Théo du soir (thème avancé, exercice, livrable) | E4: n8n + Claude API | F4: 🔴 URGENT | G4: ✗ | H4: ✗ | I4: ✗ | J4: ─
A5: 3 | B5: 📅 Weekend Brief Romaric | C5: Sam/Dim 7h50 | D5: Brief weekend : objectifs NEXOR, prospects à contacter, workflows à construire | E5: n8n + Claude API | F5: 🔴 URGENT | G5: ✗ | H5: ✗ | I5: ✗ | J5: ─
A6: 4 | B6: 📊 Bilan hebdo auto | C6: Dim 21h | D6: Compile les sessions ✓ Alegria/Théo + CA NEXOR semaine + actions semaine suivante | E6: n8n + Notion + Claude | F6: 🟠 Haute | G6: ✗ | H6: ✗ | I6: ✗ | J6: ─
A7: 5 | B7: 🎯 Prospection LinkedIn | C7: Lun+Mer+Ven 9h | D7: Génère 10 messages LinkedIn personnalisés DSI/DG cibles + les programme via API | E7: n8n + Claude + LI | F7: 🔴 URGENT | G7: ✗ | H7: ✗ | I7: ✗ | J7: 500/sem
A8: 6 | B8: 📧 Suivi prospects auto | C8: Planifié J+3 J+7 | D8: Relance automatique prospects sans réponse après 3 et 7 jours | E8: n8n + Gmail + Claude | F8: 🔴 URGENT | G8: ✗ | H8: ✗ | I8: ✗ | J8: 300/relance
A9: 7 | B9: 📝 Contenu LinkedIn auto | C9: Mer 8h | D9: Génère 2 posts LinkedIn semaine (IA+NoCode+réseau) avec image via Pillow | E9: n8n + Claude + Pillow | F9: 🟠 Haute | G9: ✗ | H9: ✗ | I9: ✗ | J9: ─
A10: 8 | B10: 🔔 Alerte ORNET tréso | C10: Quotidien 8h | D10: Vérifie le solde bancaire ORNET et alerte si < seuil critique | E10: n8n + API Banque | F10: 🟠 Haute | G10: ✗ | H10: ✗ | I10: ✗ | J10: ─
A11: 9 | B11: 📋 Rapport WifiAudit auto | C11: Webhook upload | D11: Reçoit un export CatC/WLC → analyse → génère rapport PDF → envoie client | E11: n8n + Python + Claude | F11: 🟡 Moyenne | G11: ✗ | H11: ✗ | I11: ✗ | J11: 299-599€/rapport
A12: 10 | B12: 🤖 Agent qualif leads | C12: Email entrant | D12: Qualifie automatiquement les leads entrants : score + fiche Notion + réponse auto | E12: n8n + Claude + Notion | F12: 🟡 Moyenne | G12: ✗ | H12: ✗ | I12: ✗ | J12: valeur pipeline
A13: 11 | B13: 🔄 Onboarding client NEXOR | C13: Paiement Stripe | D13: Nouveau client → email bienvenue + accès + fiche Notion + rappel J+3 | E13: n8n + Stripe + Notion | F13: 🟡 Moyenne | G13: ✗ | H13: ✗ | I13: ✗ | J13: ─
A14: 12 | B14: 📈 KPI dashboard update | C14: Quotidien 23h | D14: Met à jour les KPIs Notion (CA, clients, sessions) depuis les sources de données | E14: n8n + Notion | F14: 🟢 Basse | G14: ✗ | H14: ✗ | I14: ✗ | J14: ─
